core/__init__.py
core/common.py
core/emailing.py
core/excel.py
core/mixins.py
core/py.typed
wardy_core-0.1.4.3.dist-info/LICENSE
wardy_core-0.1.4.3.dist-info/METADATA
wardy_core-0.1.4.3.dist-info/WHEEL
wardy_core-0.1.4.3.dist-info/RECORD
